{
   "levels" : [
      {
         "level" : "1",
	 "sublevels" : "15",
         "words" : [
            "אות",
            "אמא",
            "דגל",
            "סבא",
            "בית",
            "יפה",
            "רמי",
            "דני",
            "חנה",
            "אסי",
            "תמי",
            "עבה",
            "סכה",
            "חסה",
            "בצל",
            "סלם",
            "צב",
            "גזר",
            "שבת",
            "דג",
            "הר",
            "ים",
            "שפן",
            "נמר",
            "גמל",
            "שור",
            "פרח",
            "חצב",
            "טוב",
            "חלב",
            "מרק",
            "רגל",
            "בשר",
            "חול",
            "קיר",
            "טל",
            "פיל",
            "פנס",
            "כוס",
            "פרה",
            "תיק"
         ]
      },
      {
         "level" : "2",
	 "sublevels" : "15",
         "words" : [
            "בננה",
            "חלום",
            "שלום",
            "ספור",
            "כתה",
            "יואב",
            "טובה",
            "חסידה",
            "דגים",
            "תפוח",
            "שופר",
            "אדמה",
            "מתנה",
            "נמלה",
            "גדול",
            "נקבה",
            "שחמט",
            "דמקה",
            "נרקיס",
            "כלנית",
            "זברה",
            "כדור",
            "סבתא",
            "מורה",
            "משחק",
            "עכשו",
            "עגיות",
            "כובע",
            "פרפר",
            "קפוד",
            "קביות",
            "תותים",
            "סכריה",
            "סוס",
            "שוקו",
            "קומה",
            "תפוז",
            "כיסה",
            "תוכי",
            "פורים",
            "חנכה",
            "פסח"
         ]
      },
      {
         "level" : "3",
	 "sublevels" : "15",
         "words" : [
            "אקורדיון",
            "אויר",
            "מטוס",
            "אוירון",
            "אזעקה",
            "כל",
            "שקר",
            "תמיד",
            "אמבולנס",
            "נמלה",
            "דירה",
            "כרסה",
            "צבא",
            "דודה",
            "סתו",
            "תינוק",
            "תרמיל",
            "כדור",
            "בננה",
            "ספר",
            "סל",
            "דבורה",
            "חפושית",
            "קלמנטינה",
            "מזמרה",
            "כרובית",
            "בקבוק",
            "מטאטא",
            "מצלמה",
            "אוטובוס",
            "ברוז",
            "ספגניה",
            "מעטפה",
            "משקפת",
            "משפחה",
            "אשכולית",
            "תרנגלת",
            "זריקה",
            "מנורה",
            "מנעול",
            "מחברת",
            "אופנוע",
            "אפרסק",
            "פסנתר",
            "תלמיד",
            "שבועות",
            "טלויזיה",
            "משרוקית",
            "נחליאלי",
            "אתמול",
            "זברה"
         ]
      }
   ],
   "name" : "default-he",
   "locale" : "he",
   "description" : "Default Hebrew"
}
